{
	"metadata": {
		"dataVersion": "2",
		"matchId": "KR_6072464549",
		"participants": [
			"1ImwT0TctolPuYKyBPWlEo8SLMqMbuysVVbnBv40CP6cS_iTceDYPMt1hsY7M9PyQWAU9OzJVvyPQQ",
			"SNocXb_OEv1Th7MzG52Y5TMyovvuDm3dcEcDiIxRkfw-Lw0FtXBblKNqb2HxgilcjutwimH9cudbQA",
			"4w7jD0pSBCqsTLsdddEpFhWm-x_bXC-mp3qoA6-MMlY4zXuOvMSkO3MgI3wyxQsQMG9-05uAd-sIZA",
			"uVhifJwRN0_Gr-pl4T7pJ7GzsLuUFYpRtbHo_vvPlrPZvJyvzuMfVARHvPkJxcBhtl7SMkj5UvnyeA",
			"kdxrNvdPnQHZ57wgvNtuRT4Uyz_1e6At7mQxztdt-Q6OkiMCGIIkhEvGluKCvX5Oy_rtC3v3ZY4tAw",
			"ImMVgKMMr9KvgdRJ7zxwRuiaaasjlaWnk62ZYCAaEUpz6XX-ZD6Y2KdroX7jxG4W_OV9oQr4ruobwg",
			"xiaoKIeCVnBZj5ZXYvD1WvWCtvq_Y5MbSVUoxkmnlBcsQJLlmH03FCXxSd8s5JtbjMVB4guTRjBSFg",
			"MWdLzeAEQKhEo5jLXxBU8zzeoM4Aa2XrlXyBBaFI9Nr00cZ1wg4CZkgZqElhXizutTVTFFfyzftAwQ",
			"JWA7Wdestgs09dS6wuHMprCV0Gkjzyo0I91vyfZSqKmY8sUET_zd3w0HjC-KkaVciUx50_6dloZCLg",
			"E5tHMy4RPBUkEadyuPSZOQPOy30R-AmhnlH1cFijNtFJ0y4BzAiFt86qpWdC-iepz-OjD0_bbKgoMw"
		],
		"puuid_to_part": {
			"1ImwT0TctolPuYKyBPWlEo8SLMqMbuysVVbnBv40CP6cS_iTceDYPMt1hsY7M9PyQWAU9OzJVvyPQQ": "1",
			"SNocXb_OEv1Th7MzG52Y5TMyovvuDm3dcEcDiIxRkfw-Lw0FtXBblKNqb2HxgilcjutwimH9cudbQA": "2",
			"4w7jD0pSBCqsTLsdddEpFhWm-x_bXC-mp3qoA6-MMlY4zXuOvMSkO3MgI3wyxQsQMG9-05uAd-sIZA": "3",
			"uVhifJwRN0_Gr-pl4T7pJ7GzsLuUFYpRtbHo_vvPlrPZvJyvzuMfVARHvPkJxcBhtl7SMkj5UvnyeA": "4",
			"kdxrNvdPnQHZ57wgvNtuRT4Uyz_1e6At7mQxztdt-Q6OkiMCGIIkhEvGluKCvX5Oy_rtC3v3ZY4tAw": "5",
			"ImMVgKMMr9KvgdRJ7zxwRuiaaasjlaWnk62ZYCAaEUpz6XX-ZD6Y2KdroX7jxG4W_OV9oQr4ruobwg": "6",
			"xiaoKIeCVnBZj5ZXYvD1WvWCtvq_Y5MbSVUoxkmnlBcsQJLlmH03FCXxSd8s5JtbjMVB4guTRjBSFg": "7",
			"MWdLzeAEQKhEo5jLXxBU8zzeoM4Aa2XrlXyBBaFI9Nr00cZ1wg4CZkgZqElhXizutTVTFFfyzftAwQ": "8",
			"JWA7Wdestgs09dS6wuHMprCV0Gkjzyo0I91vyfZSqKmY8sUET_zd3w0HjC-KkaVciUx50_6dloZCLg": "9",
			"E5tHMy4RPBUkEadyuPSZOQPOy30R-AmhnlH1cFijNtFJ0y4BzAiFt86qpWdC-iepz-OjD0_bbKgoMw": "10"
		},
		"champions": {
			"1": {
				"champion": 32,
				"position": "MIDDLE",
				"teamId": 100,
				"win": false,
				"perk": [
					162,
					168,
					171,
					172,
					194,
					196
				]
			},
			"2": {
				"champion": 156,
				"position": "JUNGLE",
				"teamId": 100,
				"win": false,
				"perk": [
					178,
					180,
					182,
					185,
					168,
					175
				]
			},
			"3": {
				"champion": 124,
				"position": "TOP",
				"teamId": 100,
				"win": false,
				"perk": [
					190,
					193,
					195,
					200,
					184,
					185
				]
			},
			"4": {
				"champion": 70,
				"position": "BOTTOM",
				"teamId": 100,
				"win": false,
				"perk": [
					188,
					194,
					197,
					198,
					185,
					184
				]
			},
			"5": {
				"champion": 81,
				"position": "UTILITY",
				"teamId": 100,
				"win": false,
				"perk": [
					162,
					167,
					169,
					172,
					180,
					184
				]
			},
			"6": {
				"champion": 96,
				"position": "TOP",
				"teamId": 200,
				"win": true,
				"perk": [
					215,
					217,
					220,
					222,
					166,
					172
				]
			},
			"7": {
				"champion": 92,
				"position": "JUNGLE",
				"teamId": 200,
				"win": true,
				"perk": [
					191,
					193,
					196,
					200,
					180,
					185
				]
			},
			"8": {
				"champion": 2,
				"position": "MIDDLE",
				"teamId": 200,
				"win": true,
				"perk": [
					191,
					194,
					195,
					200,
					222,
					216
				]
			},
			"9": {
				"champion": 117,
				"position": "BOTTOM",
				"teamId": 200,
				"win": true,
				"perk": [
					188,
					194,
					197,
					198,
					167,
					172
				]
			},
			"10": {
				"champion": 101,
				"position": "UTILITY",
				"teamId": 200,
				"win": true,
				"perk": [
					203,
					206,
					208,
					211,
					184,
					185
				]
			}
		}
	},
	"info": {
		"frames": [
			{
				"participantFrames": {
					"1": {
						"currentGold": 500,
						"totalGold": 500,
						"items": []
					},
					"2": {
						"currentGold": 500,
						"totalGold": 500,
						"items": []
					},
					"3": {
						"currentGold": 500,
						"totalGold": 500,
						"items": []
					},
					"4": {
						"currentGold": 500,
						"totalGold": 500,
						"items": []
					},
					"5": {
						"currentGold": 500,
						"totalGold": 500,
						"items": []
					},
					"6": {
						"currentGold": 500,
						"totalGold": 500,
						"items": []
					},
					"7": {
						"currentGold": 500,
						"totalGold": 500,
						"items": []
					},
					"8": {
						"currentGold": 500,
						"totalGold": 500,
						"items": []
					},
					"9": {
						"currentGold": 500,
						"totalGold": 500,
						"items": []
					},
					"10": {
						"currentGold": 500,
						"totalGold": 500,
						"items": []
					}
				}
			},
			{
				"participantFrames": {
					"1": {
						"currentGold": 0,
						"totalGold": 500,
						"items": []
					},
					"2": {
						"currentGold": 0,
						"totalGold": 500,
						"items": []
					},
					"3": {
						"currentGold": 0,
						"totalGold": 500,
						"items": []
					},
					"4": {
						"currentGold": 0,
						"totalGold": 500,
						"items": []
					},
					"5": {
						"currentGold": 0,
						"totalGold": 500,
						"items": []
					},
					"6": {
						"currentGold": 0,
						"totalGold": 500,
						"items": []
					},
					"7": {
						"currentGold": 0,
						"totalGold": 500,
						"items": []
					},
					"8": {
						"currentGold": 0,
						"totalGold": 500,
						"items": []
					},
					"9": {
						"currentGold": 0,
						"totalGold": 500,
						"items": []
					},
					"10": {
						"currentGold": 0,
						"totalGold": 500,
						"items": []
					}
				}
			},
			{
				"participantFrames": {
					"1": {
						"currentGold": 42,
						"totalGold": 542,
						"items": []
					},
					"2": {
						"currentGold": 211,
						"totalGold": 711,
						"items": []
					},
					"3": {
						"currentGold": 42,
						"totalGold": 542,
						"items": []
					},
					"4": {
						"currentGold": 56,
						"totalGold": 556,
						"items": []
					},
					"5": {
						"currentGold": 43,
						"totalGold": 543,
						"items": []
					},
					"6": {
						"currentGold": 84,
						"totalGold": 584,
						"items": []
					},
					"7": {
						"currentGold": 211,
						"totalGold": 711,
						"items": []
					},
					"8": {
						"currentGold": 91,
						"totalGold": 591,
						"items": []
					},
					"9": {
						"currentGold": 84,
						"totalGold": 584,
						"items": []
					},
					"10": {
						"currentGold": 83,
						"totalGold": 583,
						"items": []
					}
				}
			},
			{
				"participantFrames": {
					"1": {
						"currentGold": 388,
						"totalGold": 888,
						"items": []
					},
					"2": {
						"currentGold": 613,
						"totalGold": 1113,
						"items": []
					},
					"3": {
						"currentGold": 276,
						"totalGold": 776,
						"items": []
					},
					"4": {
						"currentGold": 332,
						"totalGold": 832,
						"items": []
					},
					"5": {
						"currentGold": 197,
						"totalGold": 697,
						"items": []
					},
					"6": {
						"currentGold": 497,
						"totalGold": 997,
						"items": []
					},
					"7": {
						"currentGold": 83,
						"totalGold": 1358,
						"items": []
					},
					"8": {
						"currentGold": 438,
						"totalGold": 948,
						"items": []
					},
					"9": {
						"currentGold": 503,
						"totalGold": 1003,
						"items": []
					},
					"10": {
						"currentGold": 417,
						"totalGold": 917,
						"items": []
					}
				}
			},
			{
				"participantFrames": {
					"1": {
						"currentGold": 1085,
						"totalGold": 1595,
						"items": []
					},
					"2": {
						"currentGold": 1002,
						"totalGold": 1502,
						"items": []
					},
					"3": {
						"currentGold": 592,
						"totalGold": 1092,
						"items": []
					},
					"4": {
						"currentGold": 40,
						"totalGold": 1190,
						"items": []
					},
					"5": {
						"currentGold": 352,
						"totalGold": 852,
						"items": []
					},
					"6": {
						"currentGold": 1095,
						"totalGold": 1595,
						"items": []
					},
					"7": {
						"currentGold": 391,
						"totalGold": 1666,
						"items": []
					},
					"8": {
						"currentGold": 202,
						"totalGold": 1162,
						"items": []
					},
					"9": {
						"currentGold": 62,
						"totalGold": 1312,
						"items": []
					},
					"10": {
						"currentGold": 77,
						"totalGold": 1052,
						"items": []
					}
				}
			},
			{
				"participantFrames": {
					"1": {
						"currentGold": 157,
						"totalGold": 1717,
						"items": []
					},
					"2": {
						"currentGold": 84,
						"totalGold": 1809,
						"items": []
					},
					"3": {
						"currentGold": 198,
						"totalGold": 1298,
						"items": []
					},
					"4": {
						"currentGold": 372,
						"totalGold": 1522,
						"items": []
					},
					"5": {
						"currentGold": 546,
						"totalGold": 1046,
						"items": []
					},
					"6": {
						"currentGold": 113,
						"totalGold": 1738,
						"items": []
					},
					"7": {
						"currentGold": 590,
						"totalGold": 1865,
						"items": []
					},
					"8": {
						"currentGold": 594,
						"totalGold": 1564,
						"items": []
					},
					"9": {
						"currentGold": 450,
						"totalGold": 1700,
						"items": []
					},
					"10": {
						"currentGold": 291,
						"totalGold": 1266,
						"items": []
					}
				}
			},
			{
				"participantFrames": {
					"1": {
						"currentGold": 469,
						"totalGold": 2039,
						"items": []
					},
					"2": {
						"currentGold": 433,
						"totalGold": 2158,
						"items": [
							75
						]
					},
					"3": {
						"currentGold": 454,
						"totalGold": 1554,
						"items": []
					},
					"4": {
						"currentGold": 649,
						"totalGold": 1799,
						"items": []
					},
					"5": {
						"currentGold": 681,
						"totalGold": 1181,
						"items": []
					},
					"6": {
						"currentGold": 519,
						"totalGold": 2144,
						"items": [
							6
						]
					},
					"7": {
						"currentGold": 898,
						"totalGold": 2173,
						"items": []
					},
					"8": {
						"currentGold": 955,
						"totalGold": 1935,
						"items": []
					},
					"9": {
						"currentGold": 699,
						"totalGold": 1949,
						"items": []
					},
					"10": {
						"currentGold": 506,
						"totalGold": 1481,
						"items": []
					}
				}
			},
			{
				"participantFrames": {
					"1": {
						"currentGold": 296,
						"totalGold": 2301,
						"items": []
					},
					"2": {
						"currentGold": 585,
						"totalGold": 2310,
						"items": [
							75
						]
					},
					"3": {
						"currentGold": 1151,
						"totalGold": 2251,
						"items": []
					},
					"4": {
						"currentGold": 27,
						"totalGold": 2127,
						"items": []
					},
					"5": {
						"currentGold": 130,
						"totalGold": 1315,
						"items": []
					},
					"6": {
						"currentGold": 236,
						"totalGold": 2461,
						"items": [
							6
						]
					},
					"7": {
						"currentGold": 136,
						"totalGold": 2511,
						"items": []
					},
					"8": {
						"currentGold": 111,
						"totalGold": 2141,
						"items": []
					},
					"9": {
						"currentGold": 84,
						"totalGold": 2134,
						"items": []
					},
					"10": {
						"currentGold": 176,
						"totalGold": 1676,
						"items": []
					}
				}
			},
			{
				"participantFrames": {
					"1": {
						"currentGold": 631,
						"totalGold": 2646,
						"items": []
					},
					"2": {
						"currentGold": 106,
						"totalGold": 2656,
						"items": [
							75
						]
					},
					"3": {
						"currentGold": 217,
						"totalGold": 2442,
						"items": []
					},
					"4": {
						"currentGold": 20,
						"totalGold": 2420,
						"items": [
							138
						]
					},
					"5": {
						"currentGold": 49,
						"totalGold": 1899,
						"items": []
					},
					"6": {
						"currentGold": 616,
						"totalGold": 2841,
						"items": [
							6
						]
					},
					"7": {
						"currentGold": 142,
						"totalGold": 2917,
						"items": [
							123
						]
					},
					"8": {
						"currentGold": 516,
						"totalGold": 2556,
						"items": [
							81
						]
					},
					"9": {
						"currentGold": 880,
						"totalGold": 2930,
						"items": [
							75
						]
					},
					"10": {
						"currentGold": 860,
						"totalGold": 2360,
						"items": []
					}
				}
			},
			{
				"participantFrames": {
					"1": {
						"currentGold": 1377,
						"totalGold": 3392,
						"items": []
					},
					"2": {
						"currentGold": 438,
						"totalGold": 2988,
						"items": [
							75
						]
					},
					"3": {
						"currentGold": 629,
						"totalGold": 2854,
						"items": [
							33
						]
					},
					"4": {
						"currentGold": 803,
						"totalGold": 3203,
						"items": [
							138
						]
					},
					"5": {
						"currentGold": 344,
						"totalGold": 2194,
						"items": [
							119
						]
					},
					"6": {
						"currentGold": 39,
						"totalGold": 2964,
						"items": [
							6
						]
					},
					"7": {
						"currentGold": 349,
						"totalGold": 3124,
						"items": [
							123,
							74
						]
					},
					"8": {
						"currentGold": 394,
						"totalGold": 2784,
						"items": [
							81
						]
					},
					"9": {
						"currentGold": 173,
						"totalGold": 3473,
						"items": [
							75
						]
					},
					"10": {
						"currentGold": 335,
						"totalGold": 2560,
						"items": []
					}
				}
			},
			{
				"participantFrames": {
					"1": {
						"currentGold": 88,
						"totalGold": 3668,
						"items": []
					},
					"2": {
						"currentGold": 1130,
						"totalGold": 3680,
						"items": [
							75
						]
					},
					"3": {
						"currentGold": 209,
						"totalGold": 3109,
						"items": [
							33
						]
					},
					"4": {
						"currentGold": 134,
						"totalGold": 3409,
						"items": [
							138
						]
					},
					"5": {
						"currentGold": 578,
						"totalGold": 2428,
						"items": [
							119
						]
					},
					"6": {
						"currentGold": 520,
						"totalGold": 3445,
						"items": [
							6,
							5
						]
					},
					"7": {
						"currentGold": 888,
						"totalGold": 3663,
						"items": [
							123,
							74
						]
					},
					"8": {
						"currentGold": 651,
						"totalGold": 3116,
						"items": [
							81
						]
					},
					"9": {
						"currentGold": 265,
						"totalGold": 3715,
						"items": [
							75,
							138
						]
					},
					"10": {
						"currentGold": 106,
						"totalGold": 2731,
						"items": [
							87
						]
					}
				}
			},
			{
				"participantFrames": {
					"1": {
						"currentGold": 416,
						"totalGold": 3996,
						"items": [
							21,
							60
						]
					},
					"2": {
						"currentGold": -3,
						"totalGold": 3897,
						"items": [
							75
						]
					},
					"3": {
						"currentGold": 680,
						"totalGold": 3580,
						"items": [
							33,
							135
						]
					},
					"4": {
						"currentGold": 144,
						"totalGold": 3644,
						"items": [
							138,
							3
						]
					},
					"5": {
						"currentGold": 353,
						"totalGold": 2603,
						"items": [
							119
						]
					},
					"6": {
						"currentGold": 778,
						"totalGold": 3703,
						"items": [
							6,
							5
						]
					},
					"7": {
						"currentGold": 1647,
						"totalGold": 4422,
						"items": [
							123,
							74
						]
					},
					"8": {
						"currentGold": 118,
						"totalGold": 3468,
						"items": [
							81
						]
					},
					"9": {
						"currentGold": 968,
						"totalGold": 4418,
						"items": [
							75,
							138
						]
					},
					"10": {
						"currentGold": 733,
						"totalGold": 3358,
						"items": [
							87,
							39
						]
					}
				}
			},
			{
				"participantFrames": {
					"1": {
						"currentGold": 601,
						"totalGold": 4181,
						"items": [
							21,
							60
						]
					},
					"2": {
						"currentGold": 228,
						"totalGold": 4128,
						"items": [
							145
						]
					},
					"3": {
						"currentGold": 1091,
						"totalGold": 3991,
						"items": [
							33,
							135
						]
					},
					"4": {
						"currentGold": 221,
						"totalGold": 3796,
						"items": [
							138,
							3
						]
					},
					"5": {
						"currentGold": 17,
						"totalGold": 2807,
						"items": [
							119,
							39
						]
					},
					"6": {
						"currentGold": 1432,
						"totalGold": 4357,
						"items": [
							6,
							5
						]
					},
					"7": {
						"currentGold": 1896,
						"totalGold": 4671,
						"items": [
							123,
							74
						]
					},
					"8": {
						"currentGold": 835,
						"totalGold": 4195,
						"items": [
							81,
							21
						]
					},
					"9": {
						"currentGold": 1369,
						"totalGold": 4819,
						"items": [
							75,
							138
						]
					},
					"10": {
						"currentGold": 954,
						"totalGold": 3579,
						"items": [
							87,
							39
						]
					}
				}
			},
			{
				"participantFrames": {
					"1": {
						"currentGold": 316,
						"totalGold": 4596,
						"items": [
							21,
							60
						]
					},
					"2": {
						"currentGold": 835,
						"totalGold": 4735,
						"items": [
							145
						]
					},
					"3": {
						"currentGold": 1395,
						"totalGold": 4295,
						"items": [
							33,
							135
						]
					},
					"4": {
						"currentGold": 713,
						"totalGold": 4288,
						"items": [
							138,
							3
						]
					},
					"5": {
						"currentGold": 391,
						"totalGold": 3181,
						"items": [
							106
						]
					},
					"6": {
						"currentGold": 247,
						"totalGold": 4647,
						"items": [
							6,
							5
						]
					},
					"7": {
						"currentGold": 203,
						"totalGold": 4893,
						"items": [
							123,
							74
						]
					},
					"8": {
						"currentGold": 438,
						"totalGold": 4618,
						"items": [
							81,
							21
						]
					},
					"9": {
						"currentGold": 708,
						"totalGold": 5033,
						"items": [
							75,
							138
						]
					},
					"10": {
						"currentGold": 505,
						"totalGold": 4080,
						"items": [
							87,
							39
						]
					}
				}
			},
			{
				"participantFrames": {
					"1": {
						"currentGold": 523,
						"totalGold": 4803,
						"items": [
							21,
							60,
							94
						]
					},
					"2": {
						"currentGold": 1506,
						"totalGold": 5406,
						"items": [
							145
						]
					},
					"3": {
						"currentGold": 1823,
						"totalGold": 4723,
						"items": [
							33,
							135
						]
					},
					"4": {
						"currentGold": 1226,
						"totalGold": 4801,
						"items": [
							138,
							3
						]
					},
					"5": {
						"currentGold": 853,
						"totalGold": 3643,
						"items": [
							106
						]
					},
					"6": {
						"currentGold": 571,
						"totalGold": 4971,
						"items": [
							83
						]
					},
					"7": {
						"currentGold": 585,
						"totalGold": 5275,
						"items": [
							129,
							63
						]
					},
					"8": {
						"currentGold": 1010,
						"totalGold": 5200,
						"items": [
							81,
							21,
							1
						]
					},
					"9": {
						"currentGold": 345,
						"totalGold": 5970,
						"items": [
							75,
							138,
							3
						]
					},
					"10": {
						"currentGold": 605,
						"totalGold": 4330,
						"items": [
							87,
							39,
							119
						]
					}
				}
			},
			{
				"participantFrames": {
					"1": {
						"currentGold": 939,
						"totalGold": 5219,
						"items": [
							21,
							60,
							94
						]
					},
					"2": {
						"currentGold": 134,
						"totalGold": 5774,
						"items": [
							145
						]
					},
					"3": {
						"currentGold": 699,
						"totalGold": 4999,
						"items": [
							33,
							135
						]
					},
					"4": {
						"currentGold": 145,
						"totalGold": 4995,
						"items": [
							138,
							3
						]
					},
					"5": {
						"currentGold": 253,
						"totalGold": 3854,
						"items": [
							106
						]
					},
					"6": {
						"currentGold": 1088,
						"totalGold": 5488,
						"items": [
							83
						]
					},
					"7": {
						"currentGold": 1074,
						"totalGold": 5764,
						"items": [
							129,
							63
						]
					},
					"8": {
						"currentGold": 1790,
						"totalGold": 5980,
						"items": [
							81,
							21,
							1
						]
					},
					"9": {
						"currentGold": 1771,
						"totalGold": 7396,
						"items": [
							75,
							140
						]
					},
					"10": {
						"currentGold": 1309,
						"totalGold": 5034,
						"items": [
							87,
							39,
							119
						]
					}
				}
			},
			{
				"participantFrames": {
					"1": {
						"currentGold": 227,
						"totalGold": 5642,
						"items": [
							21,
							60,
							94
						]
					},
					"2": {
						"currentGold": 407,
						"totalGold": 6047,
						"items": [
							145,
							75,
							87
						]
					},
					"3": {
						"currentGold": 278,
						"totalGold": 5378,
						"items": [
							33,
							135,
							58
						]
					},
					"4": {
						"currentGold": 81,
						"totalGold": 5231,
						"items": [
							139,
							87
						]
					},
					"5": {
						"currentGold": 607,
						"totalGold": 4207,
						"items": [
							106
						]
					},
					"6": {
						"currentGold": 1624,
						"totalGold": 6024,
						"items": [
							83
						]
					},
					"7": {
						"currentGold": 1847,
						"totalGold": 6537,
						"items": [
							129,
							63
						]
					},
					"8": {
						"currentGold": 146,
						"totalGold": 6161,
						"items": [
							81,
							21,
							1
						]
					},
					"9": {
						"currentGold": 180,
						"totalGold": 8020,
						"items": [
							75,
							140
						]
					},
					"10": {
						"currentGold": 180,
						"totalGold": 5205,
						"items": [
							87,
							39,
							119
						]
					}
				}
			},
			{
				"participantFrames": {
					"1": {
						"currentGold": 688,
						"totalGold": 6103,
						"items": [
							21,
							86
						]
					},
					"2": {
						"currentGold": 845,
						"totalGold": 6485,
						"items": [
							145,
							75,
							87
						]
					},
					"3": {
						"currentGold": 568,
						"totalGold": 5668,
						"items": [
							33,
							40
						]
					},
					"4": {
						"currentGold": 398,
						"totalGold": 5548,
						"items": [
							139,
							87
						]
					},
					"5": {
						"currentGold": 127,
						"totalGold": 4347,
						"items": [
							106
						]
					},
					"6": {
						"currentGold": 565,
						"totalGold": 6265,
						"items": [
							83
						]
					},
					"7": {
						"currentGold": 473,
						"totalGold": 6738,
						"items": [
							129,
							63
						]
					},
					"8": {
						"currentGold": 662,
						"totalGold": 6677,
						"items": [
							21,
							82
						]
					},
					"9": {
						"currentGold": 455,
						"totalGold": 8295,
						"items": [
							140,
							18,
							3
						]
					},
					"10": {
						"currentGold": 321,
						"totalGold": 5346,
						"items": [
							87,
							10
						]
					}
				}
			},
			{
				"participantFrames": {
					"1": {
						"currentGold": 1010,
						"totalGold": 7290,
						"items": [
							21,
							86
						]
					},
					"2": {
						"currentGold": 1698,
						"totalGold": 7338,
						"items": [
							145,
							75,
							87
						]
					},
					"3": {
						"currentGold": 871,
						"totalGold": 5971,
						"items": [
							33,
							40
						]
					},
					"4": {
						"currentGold": 369,
						"totalGold": 5894,
						"items": [
							139,
							87
						]
					},
					"5": {
						"currentGold": 1159,
						"totalGold": 5379,
						"items": [
							106,
							87
						]
					},
					"6": {
						"currentGold": 1183,
						"totalGold": 6883,
						"items": [
							83,
							84
						]
					},
					"7": {
						"currentGold": 195,
						"totalGold": 6860,
						"items": [
							129,
							63,
							74
						]
					},
					"8": {
						"currentGold": 1492,
						"totalGold": 7507,
						"items": [
							21,
							82
						]
					},
					"9": {
						"currentGold": 86,
						"totalGold": 8701,
						"items": [
							140,
							18,
							3
						]
					},
					"10": {
						"currentGold": 96,
						"totalGold": 5596,
						"items": [
							87,
							10
						]
					}
				}
			},
			{
				"participantFrames": {
					"1": {
						"currentGold": 525,
						"totalGold": 7545,
						"items": [
							21,
							86,
							103
						]
					},
					"2": {
						"currentGold": -194,
						"totalGold": 7746,
						"items": [
							145,
							75,
							87
						]
					},
					"3": {
						"currentGold": 73,
						"totalGold": 6213,
						"items": [
							33,
							40
						]
					},
					"4": {
						"currentGold": 238,
						"totalGold": 6163,
						"items": [
							139,
							87
						]
					},
					"5": {
						"currentGold": 499,
						"totalGold": 5569,
						"items": [
							106,
							87
						]
					},
					"6": {
						"currentGold": 1644,
						"totalGold": 7284,
						"items": [
							83,
							84
						]
					},
					"7": {
						"currentGold": 469,
						"totalGold": 7134,
						"items": [
							129,
							63,
							74,
							39
						]
					},
					"8": {
						"currentGold": 734,
						"totalGold": 7819,
						"items": [
							21,
							82
						]
					},
					"9": {
						"currentGold": 668,
						"totalGold": 9283,
						"items": [
							140,
							18,
							143
						]
					},
					"10": {
						"currentGold": 266,
						"totalGold": 5766,
						"items": [
							87,
							10,
							39
						]
					}
				}
			},
			{
				"participantFrames": {
					"1": {
						"currentGold": 235,
						"totalGold": 8330,
						"items": [
							21,
							86,
							103,
							60
						]
					},
					"2": {
						"currentGold": 1,
						"totalGold": 7941,
						"items": [
							145,
							87,
							79
						]
					},
					"3": {
						"currentGold": 257,
						"totalGold": 6472,
						"items": [
							33,
							40,
							38
						]
					},
					"4": {
						"currentGold": 474,
						"totalGold": 6399,
						"items": [
							139,
							87
						]
					},
					"5": {
						"currentGold": 754,
						"totalGold": 5824,
						"items": [
							106,
							87,
							1
						]
					},
					"6": {
						"currentGold": 218,
						"totalGold": 7458,
						"items": [
							83,
							84
						]
					},
					"7": {
						"currentGold": 836,
						"totalGold": 7501,
						"items": [
							129,
							63,
							74,
							39
						]
					},
					"8": {
						"currentGold": 291,
						"totalGold": 7991,
						"items": [
							21,
							82,
							8
						]
					},
					"9": {
						"currentGold": 461,
						"totalGold": 10126,
						"items": [
							140,
							18,
							143
						]
					},
					"10": {
						"currentGold": 267,
						"totalGold": 6181,
						"items": [
							87,
							10,
							39
						]
					}
				}
			},
			{
				"participantFrames": {
					"1": {
						"currentGold": 472,
						"totalGold": 8566,
						"items": [
							21,
							86,
							132
						]
					},
					"2": {
						"currentGold": 343,
						"totalGold": 8283,
						"items": [
							145,
							87,
							79
						]
					},
					"3": {
						"currentGold": 596,
						"totalGold": 6811,
						"items": [
							33,
							40,
							38
						]
					},
					"4": {
						"currentGold": 897,
						"totalGold": 6822,
						"items": [
							139,
							87
						]
					},
					"5": {
						"currentGold": 915,
						"totalGold": 5985,
						"items": [
							106,
							87,
							1
						]
					},
					"6": {
						"currentGold": 315,
						"totalGold": 7630,
						"items": [
							83,
							85
						]
					},
					"7": {
						"currentGold": 1309,
						"totalGold": 7974,
						"items": [
							129,
							63,
							74,
							39
						]
					},
					"8": {
						"currentGold": 1121,
						"totalGold": 8821,
						"items": [
							21,
							82,
							8,
							81
						]
					},
					"9": {
						"currentGold": 1258,
						"totalGold": 10923,
						"items": [
							140,
							18,
							143,
							51
						]
					},
					"10": {
						"currentGold": 517,
						"totalGold": 6432,
						"items": [
							87,
							10,
							39
						]
					}
				}
			},
			{
				"participantFrames": {
					"1": {
						"currentGold": 152,
						"totalGold": 8947,
						"items": [
							21,
							86,
							132
						]
					},
					"2": {
						"currentGold": 974,
						"totalGold": 8914,
						"items": [
							145,
							87,
							79
						]
					},
					"3": {
						"currentGold": 778,
						"totalGold": 6993,
						"items": [
							33,
							40,
							38
						]
					},
					"4": {
						"currentGold": 1319,
						"totalGold": 7244,
						"items": [
							139,
							87
						]
					},
					"5": {
						"currentGold": 1175,
						"totalGold": 6245,
						"items": [
							106,
							87,
							1
						]
					},
					"6": {
						"currentGold": 668,
						"totalGold": 7983,
						"items": [
							83,
							85
						]
					},
					"7": {
						"currentGold": 526,
						"totalGold": 8466,
						"items": [
							129,
							63,
							74,
							39
						]
					},
					"8": {
						"currentGold": 164,
						"totalGold": 8999,
						"items": [
							21,
							82,
							8,
							81
						]
					},
					"9": {
						"currentGold": 2031,
						"totalGold": 11695,
						"items": [
							140,
							18,
							143,
							51
						]
					},
					"10": {
						"currentGold": 207,
						"totalGold": 6672,
						"items": [
							87,
							10,
							39
						]
					}
				}
			},
			{
				"participantFrames": {
					"1": {
						"currentGold": 866,
						"totalGold": 10311,
						"items": [
							21,
							86,
							132
						]
					},
					"2": {
						"currentGold": 34,
						"totalGold": 9149,
						"items": [
							145,
							87,
							79
						]
					},
					"3": {
						"currentGold": 59,
						"totalGold": 7174,
						"items": [
							33,
							40,
							38
						]
					},
					"4": {
						"currentGold": 469,
						"totalGold": 7969,
						"items": [
							139,
							87
						]
					},
					"5": {
						"currentGold": 103,
						"totalGold": 6763,
						"items": [
							106,
							87,
							1
						]
					},
					"6": {
						"currentGold": 191,
						"totalGold": 8106,
						"items": [
							83,
							85
						]
					},
					"7": {
						"currentGold": 273,
						"totalGold": 8638,
						"items": [
							129,
							63,
							41
						]
					},
					"8": {
						"currentGold": 303,
						"totalGold": 9788,
						"items": [
							21,
							82,
							122
						]
					},
					"9": {
						"currentGold": 103,
						"totalGold": 11843,
						"items": [
							140,
							18,
							143,
							51
						]
					},
					"10": {
						"currentGold": 498,
						"totalGold": 6963,
						"items": [
							87,
							10,
							39,
							102
						]
					}
				}
			},
			{
				"participantFrames": {
					"1": {
						"currentGold": 348,
						"totalGold": 10552,
						"items": [
							21,
							86,
							132,
							65
						]
					},
					"2": {
						"currentGold": 501,
						"totalGold": 9616,
						"items": [
							145,
							87,
							79,
							75
						]
					},
					"3": {
						"currentGold": 418,
						"totalGold": 7533,
						"items": [
							33,
							40,
							38,
							2
						]
					},
					"4": {
						"currentGold": 870,
						"totalGold": 8370,
						"items": [
							139,
							87,
							54
						]
					},
					"5": {
						"currentGold": 289,
						"totalGold": 6949,
						"items": [
							106,
							87,
							76
						]
					},
					"6": {
						"currentGold": 810,
						"totalGold": 8725,
						"items": [
							83,
							85
						]
					},
					"7": {
						"currentGold": 871,
						"totalGold": 9236,
						"items": [
							129,
							63,
							41
						]
					},
					"8": {
						"currentGold": 921,
						"totalGold": 10406,
						"items": [
							21,
							82,
							122,
							11
						]
					},
					"9": {
						"currentGold": 970,
						"totalGold": 12710,
						"items": [
							140,
							18,
							143,
							32,
							3
						]
					},
					"10": {
						"currentGold": 818,
						"totalGold": 7283,
						"items": [
							87,
							10,
							39,
							102
						]
					}
				}
			},
			{
				"participantFrames": {
					"1": {
						"currentGold": 471,
						"totalGold": 10676,
						"items": [
							21,
							86,
							132,
							65,
							60
						]
					},
					"2": {
						"currentGold": 1214,
						"totalGold": 10329,
						"items": [
							145,
							87,
							79,
							75
						]
					},
					"3": {
						"currentGold": 542,
						"totalGold": 7657,
						"items": [
							33,
							40,
							38,
							2
						]
					},
					"4": {
						"currentGold": 210,
						"totalGold": 8585,
						"items": [
							139,
							87,
							54
						]
					},
					"5": {
						"currentGold": 595,
						"totalGold": 7255,
						"items": [
							106,
							87,
							76
						]
					},
					"6": {
						"currentGold": 1511,
						"totalGold": 9426,
						"items": [
							83,
							85
						]
					},
					"7": {
						"currentGold": 1369,
						"totalGold": 9734,
						"items": [
							129,
							63,
							41
						]
					},
					"8": {
						"currentGold": 2489,
						"totalGold": 11973,
						"items": [
							21,
							82,
							122,
							11
						]
					},
					"9": {
						"currentGold": 2084,
						"totalGold": 13823,
						"items": [
							140,
							18,
							143,
							32,
							3
						]
					},
					"10": {
						"currentGold": 535,
						"totalGold": 7774,
						"items": [
							87,
							10,
							39,
							102
						]
					}
				}
			},
			{
				"participantFrames": {
					"1": {
						"currentGold": 511,
						"totalGold": 10716,
						"items": [
							21,
							86,
							132,
							65,
							60
						]
					},
					"2": {
						"currentGold": 1254,
						"totalGold": 10369,
						"items": [
							145,
							87,
							79,
							75
						]
					},
					"3": {
						"currentGold": 581,
						"totalGold": 7696,
						"items": [
							33,
							40,
							38,
							2
						]
					},
					"4": {
						"currentGold": 249,
						"totalGold": 8624,
						"items": [
							139,
							87,
							54,
							3
						]
					},
					"5": {
						"currentGold": 641,
						"totalGold": 7301,
						"items": [
							106,
							87,
							76
						]
					},
					"6": {
						"currentGold": 1851,
						"totalGold": 9766,
						"items": [
							83,
							85
						]
					},
					"7": {
						"currentGold": 34,
						"totalGold": 9774,
						"items": [
							129,
							63,
							41
						]
					},
					"8": {
						"currentGold": 2666,
						"totalGold": 12150,
						"items": [
							21,
							82,
							122,
							11
						]
					},
					"9": {
						"currentGold": 2507,
						"totalGold": 14246,
						"items": [
							140,
							18,
							143,
							32,
							3
						]
					},
					"10": {
						"currentGold": 730,
						"totalGold": 7970,
						"items": [
							87,
							10,
							61
						]
					}
				}
			}
		]
	}
}