{
	"metadata": {
		"dataVersion": "2",
		"matchId": "KR_5494724897",
		"participants": [
			"k4NvY-zBw3LrxusHmzsWyy9mqoZCfbx5eZVp3ToAbRL-QGc_WPXBEU6SAYo1_o0EEVEFHSadSxKNaA",
			"AsmS0da77ZdSrKmvH0kQc2A5X_YhFgfbPywsR_r1iGzRFhbwf7rDgQKBRCwVIP9X1R5kmbedggWI0Q",
			"WxHN6C30L3Hg69ONG23RqjTe_sfj48ljFqX6V-jyVsnRffqTFuYRpjGThmI1b-EsXu1kummBysb2lA",
			"VQjUDL9N0pZRTNnodFlZuugkTA1mysCoVx5mD8OFEhs7z6ku8DQtcVYBEg_M1lb6Del5_G35Hs75RQ",
			"S-D5eoAvKB7czLopOcbOrW-TW00YFm9cYUq7dJ1Zoa3ygz3ywXBsktYkqQra3b0kFoUoHGMtsOEg-w",
			"R7jiKpJR2SjNSklsbPbOVwXDK2fZ-LmkzskbRO44NvOSfY_iI7ecTJNgOBe74JD-yO-QBcd5ZmumVA",
			"QAywZI41JDy9QCWbpWniacQsTzD4AcJ7M02JBo10wZfcPDNPhgcd3JWR9kX175sAOI2CiotxXKM-VQ",
			"8cn8DyP8k88r-2f5U76CweApfO0RX10882l3jmrLCsAwJDUV_ZJs8-6zykt2XhgBLkvo2TVflAxZIA",
			"JfFy6OxUGxwPSF_sh8sHuFGg1qFZMPSbblwJhdFr0GnMiwCJ7AV-mWK9qHFFKiTIW67Wz753rIr8EA",
			"8MimN-w7aSpo2xMWltz-RUFuNAMORh4OdmGxcb0lH4r9MERSeUcjUbiAArp638NyiRejS9gO84k4wg"
		],
		"puuid_to_part": {
			"k4NvY-zBw3LrxusHmzsWyy9mqoZCfbx5eZVp3ToAbRL-QGc_WPXBEU6SAYo1_o0EEVEFHSadSxKNaA": "1",
			"AsmS0da77ZdSrKmvH0kQc2A5X_YhFgfbPywsR_r1iGzRFhbwf7rDgQKBRCwVIP9X1R5kmbedggWI0Q": "2",
			"WxHN6C30L3Hg69ONG23RqjTe_sfj48ljFqX6V-jyVsnRffqTFuYRpjGThmI1b-EsXu1kummBysb2lA": "3",
			"VQjUDL9N0pZRTNnodFlZuugkTA1mysCoVx5mD8OFEhs7z6ku8DQtcVYBEg_M1lb6Del5_G35Hs75RQ": "4",
			"S-D5eoAvKB7czLopOcbOrW-TW00YFm9cYUq7dJ1Zoa3ygz3ywXBsktYkqQra3b0kFoUoHGMtsOEg-w": "5",
			"R7jiKpJR2SjNSklsbPbOVwXDK2fZ-LmkzskbRO44NvOSfY_iI7ecTJNgOBe74JD-yO-QBcd5ZmumVA": "6",
			"QAywZI41JDy9QCWbpWniacQsTzD4AcJ7M02JBo10wZfcPDNPhgcd3JWR9kX175sAOI2CiotxXKM-VQ": "7",
			"8cn8DyP8k88r-2f5U76CweApfO0RX10882l3jmrLCsAwJDUV_ZJs8-6zykt2XhgBLkvo2TVflAxZIA": "8",
			"JfFy6OxUGxwPSF_sh8sHuFGg1qFZMPSbblwJhdFr0GnMiwCJ7AV-mWK9qHFFKiTIW67Wz753rIr8EA": "9",
			"8MimN-w7aSpo2xMWltz-RUFuNAMORh4OdmGxcb0lH4r9MERSeUcjUbiAArp638NyiRejS9gO84k4wg": "10"
		},
		"champions": {
			"1": {
				"champion": 145,
				"position": "MIDDLE",
				"teamId": 100,
				"win": false,
				"perk": [
					213,
					218,
					220,
					222,
					180,
					185
				]
			},
			"2": {
				"champion": 66,
				"position": "JUNGLE",
				"teamId": 100,
				"win": false,
				"perk": [
					191,
					193,
					196,
					198,
					180,
					185
				]
			},
			"3": {
				"champion": 67,
				"position": "UTILITY",
				"teamId": 100,
				"win": false,
				"perk": [
					202,
					205,
					209,
					212,
					179,
					183
				]
			},
			"4": {
				"champion": 70,
				"position": "BOTTOM",
				"teamId": 100,
				"win": false,
				"perk": [
					188,
					194,
					197,
					198,
					180,
					184
				]
			},
			"5": {
				"champion": 115,
				"position": "TOP",
				"teamId": 100,
				"win": false,
				"perk": [
					163,
					167,
					171,
					173,
					196,
					193
				]
			},
			"6": {
				"champion": 18,
				"position": "TOP",
				"teamId": 200,
				"win": true,
				"perk": [
					201,
					206,
					208,
					212,
					184,
					185
				]
			},
			"7": {
				"champion": 95,
				"position": "JUNGLE",
				"teamId": 200,
				"win": true,
				"perk": [
					191,
					193,
					196,
					200,
					180,
					185
				]
			},
			"8": {
				"champion": 65,
				"position": "MIDDLE",
				"teamId": 200,
				"win": true,
				"perk": [
					162,
					167,
					171,
					172,
					184,
					187
				]
			},
			"9": {
				"champion": 24,
				"position": "BOTTOM",
				"teamId": 200,
				"win": true,
				"perk": [
					165,
					167,
					171,
					172,
					194,
					197
				]
			},
			"10": {
				"champion": 33,
				"position": "UTILITY",
				"teamId": 200,
				"win": true,
				"perk": [
					202,
					206,
					209,
					212,
					218,
					219
				]
			}
		}
	},
	"info": {
		"frames": [
			{
				"participantFrames": {
					"1": {
						"currentGold": 500,
						"totalGold": 500,
						"items": []
					},
					"2": {
						"currentGold": 500,
						"totalGold": 500,
						"items": []
					},
					"3": {
						"currentGold": 500,
						"totalGold": 500,
						"items": []
					},
					"4": {
						"currentGold": 500,
						"totalGold": 500,
						"items": []
					},
					"5": {
						"currentGold": 500,
						"totalGold": 500,
						"items": []
					},
					"6": {
						"currentGold": 500,
						"totalGold": 500,
						"items": []
					},
					"7": {
						"currentGold": 500,
						"totalGold": 500,
						"items": []
					},
					"8": {
						"currentGold": 500,
						"totalGold": 500,
						"items": []
					},
					"9": {
						"currentGold": 500,
						"totalGold": 500,
						"items": []
					},
					"10": {
						"currentGold": 500,
						"totalGold": 500,
						"items": []
					}
				}
			},
			{
				"participantFrames": {
					"1": {
						"currentGold": 0,
						"totalGold": 500,
						"items": []
					},
					"2": {
						"currentGold": 0,
						"totalGold": 500,
						"items": []
					},
					"3": {
						"currentGold": 0,
						"totalGold": 500,
						"items": []
					},
					"4": {
						"currentGold": 0,
						"totalGold": 500,
						"items": []
					},
					"5": {
						"currentGold": 50,
						"totalGold": 500,
						"items": []
					},
					"6": {
						"currentGold": 0,
						"totalGold": 500,
						"items": []
					},
					"7": {
						"currentGold": 0,
						"totalGold": 500,
						"items": []
					},
					"8": {
						"currentGold": 0,
						"totalGold": 500,
						"items": []
					},
					"9": {
						"currentGold": 0,
						"totalGold": 500,
						"items": []
					},
					"10": {
						"currentGold": 0,
						"totalGold": 500,
						"items": []
					}
				}
			},
			{
				"participantFrames": {
					"1": {
						"currentGold": 98,
						"totalGold": 598,
						"items": []
					},
					"2": {
						"currentGold": 160,
						"totalGold": 660,
						"items": []
					},
					"3": {
						"currentGold": 23,
						"totalGold": 523,
						"items": []
					},
					"4": {
						"currentGold": 98,
						"totalGold": 598,
						"items": []
					},
					"5": {
						"currentGold": 162,
						"totalGold": 612,
						"items": []
					},
					"6": {
						"currentGold": 63,
						"totalGold": 563,
						"items": []
					},
					"7": {
						"currentGold": 206,
						"totalGold": 706,
						"items": []
					},
					"8": {
						"currentGold": 91,
						"totalGold": 591,
						"items": []
					},
					"9": {
						"currentGold": 84,
						"totalGold": 584,
						"items": []
					},
					"10": {
						"currentGold": 33,
						"totalGold": 533,
						"items": []
					}
				}
			},
			{
				"participantFrames": {
					"1": {
						"currentGold": 803,
						"totalGold": 1313,
						"items": []
					},
					"2": {
						"currentGold": 561,
						"totalGold": 1061,
						"items": []
					},
					"3": {
						"currentGold": 199,
						"totalGold": 699,
						"items": []
					},
					"4": {
						"currentGold": 374,
						"totalGold": 874,
						"items": []
					},
					"5": {
						"currentGold": 491,
						"totalGold": 941,
						"items": []
					},
					"6": {
						"currentGold": 360,
						"totalGold": 860,
						"items": []
					},
					"7": {
						"currentGold": 501,
						"totalGold": 1001,
						"items": []
					},
					"8": {
						"currentGold": 215,
						"totalGold": 790,
						"items": []
					},
					"9": {
						"currentGold": 829,
						"totalGold": 1329,
						"items": []
					},
					"10": {
						"currentGold": 332,
						"totalGold": 832,
						"items": []
					}
				}
			},
			{
				"participantFrames": {
					"1": {
						"currentGold": 89,
						"totalGold": 1499,
						"items": []
					},
					"2": {
						"currentGold": 860,
						"totalGold": 1360,
						"items": []
					},
					"3": {
						"currentGold": 258,
						"totalGold": 883,
						"items": []
					},
					"4": {
						"currentGold": 760,
						"totalGold": 1260,
						"items": []
					},
					"5": {
						"currentGold": 334,
						"totalGold": 1259,
						"items": []
					},
					"6": {
						"currentGold": 704,
						"totalGold": 1204,
						"items": []
					},
					"7": {
						"currentGold": 837,
						"totalGold": 1337,
						"items": []
					},
					"8": {
						"currentGold": 471,
						"totalGold": 1046,
						"items": []
					},
					"9": {
						"currentGold": 68,
						"totalGold": 1543,
						"items": []
					},
					"10": {
						"currentGold": 73,
						"totalGold": 998,
						"items": []
					}
				}
			},
			{
				"participantFrames": {
					"1": {
						"currentGold": 460,
						"totalGold": 1880,
						"items": [
							60
						]
					},
					"2": {
						"currentGold": 1072,
						"totalGold": 1572,
						"items": []
					},
					"3": {
						"currentGold": 380,
						"totalGold": 1080,
						"items": []
					},
					"4": {
						"currentGold": 220,
						"totalGold": 1445,
						"items": []
					},
					"5": {
						"currentGold": 176,
						"totalGold": 1451,
						"items": []
					},
					"6": {
						"currentGold": 1273,
						"totalGold": 1773,
						"items": []
					},
					"7": {
						"currentGold": 259,
						"totalGold": 1709,
						"items": []
					},
					"8": {
						"currentGold": 821,
						"totalGold": 1406,
						"items": []
					},
					"9": {
						"currentGold": 491,
						"totalGold": 1966,
						"items": [
							6
						]
					},
					"10": {
						"currentGold": 312,
						"totalGold": 1237,
						"items": []
					}
				}
			},
			{
				"participantFrames": {
					"1": {
						"currentGold": 709,
						"totalGold": 2129,
						"items": [
							60
						]
					},
					"2": {
						"currentGold": 234,
						"totalGold": 1834,
						"items": []
					},
					"3": {
						"currentGold": 152,
						"totalGold": 1302,
						"items": []
					},
					"4": {
						"currentGold": 692,
						"totalGold": 1917,
						"items": []
					},
					"5": {
						"currentGold": 512,
						"totalGold": 1787,
						"items": []
					},
					"6": {
						"currentGold": 94,
						"totalGold": 1994,
						"items": []
					},
					"7": {
						"currentGold": 810,
						"totalGold": 2260,
						"items": [
							3
						]
					},
					"8": {
						"currentGold": 623,
						"totalGold": 2028,
						"items": []
					},
					"9": {
						"currentGold": 84,
						"totalGold": 2559,
						"items": [
							6
						]
					},
					"10": {
						"currentGold": 584,
						"totalGold": 1509,
						"items": []
					}
				}
			},
			{
				"participantFrames": {
					"1": {
						"currentGold": 510,
						"totalGold": 2365,
						"items": [
							60
						]
					},
					"2": {
						"currentGold": 104,
						"totalGold": 2054,
						"items": [
							123
						]
					},
					"3": {
						"currentGold": 286,
						"totalGold": 1436,
						"items": []
					},
					"4": {
						"currentGold": 535,
						"totalGold": 2060,
						"items": []
					},
					"5": {
						"currentGold": 297,
						"totalGold": 1972,
						"items": []
					},
					"6": {
						"currentGold": 838,
						"totalGold": 2738,
						"items": []
					},
					"7": {
						"currentGold": 1399,
						"totalGold": 2849,
						"items": [
							3
						]
					},
					"8": {
						"currentGold": 107,
						"totalGold": 2377,
						"items": []
					},
					"9": {
						"currentGold": 461,
						"totalGold": 2936,
						"items": [
							6
						]
					},
					"10": {
						"currentGold": 826,
						"totalGold": 1751,
						"items": []
					}
				}
			},
			{
				"participantFrames": {
					"1": {
						"currentGold": 151,
						"totalGold": 3291,
						"items": [
							60
						]
					},
					"2": {
						"currentGold": 417,
						"totalGold": 2367,
						"items": [
							123
						]
					},
					"3": {
						"currentGold": 606,
						"totalGold": 1756,
						"items": []
					},
					"4": {
						"currentGold": 1083,
						"totalGold": 2608,
						"items": [
							138
						]
					},
					"5": {
						"currentGold": 103,
						"totalGold": 2353,
						"items": []
					},
					"6": {
						"currentGold": 1177,
						"totalGold": 3077,
						"items": []
					},
					"7": {
						"currentGold": 221,
						"totalGold": 3071,
						"items": [
							3
						]
					},
					"8": {
						"currentGold": 299,
						"totalGold": 2569,
						"items": [
							103
						]
					},
					"9": {
						"currentGold": 179,
						"totalGold": 3129,
						"items": [
							6
						]
					},
					"10": {
						"currentGold": 86,
						"totalGold": 1886,
						"items": []
					}
				}
			},
			{
				"participantFrames": {
					"1": {
						"currentGold": 454,
						"totalGold": 3604,
						"items": [
							60,
							1
						]
					},
					"2": {
						"currentGold": 239,
						"totalGold": 2589,
						"items": [
							123
						]
					},
					"3": {
						"currentGold": 365,
						"totalGold": 1890,
						"items": []
					},
					"4": {
						"currentGold": 180,
						"totalGold": 2730,
						"items": [
							138
						]
					},
					"5": {
						"currentGold": 435,
						"totalGold": 2685,
						"items": [
							0
						]
					},
					"6": {
						"currentGold": 1502,
						"totalGold": 3402,
						"items": []
					},
					"7": {
						"currentGold": 846,
						"totalGold": 3696,
						"items": [
							123,
							75
						]
					},
					"8": {
						"currentGold": 590,
						"totalGold": 2860,
						"items": [
							103
						]
					},
					"9": {
						"currentGold": 914,
						"totalGold": 3864,
						"items": [
							6,
							75
						]
					},
					"10": {
						"currentGold": 489,
						"totalGold": 2289,
						"items": [
							63
						]
					}
				}
			},
			{
				"participantFrames": {
					"1": {
						"currentGold": 995,
						"totalGold": 4145,
						"items": [
							60,
							1
						]
					},
					"2": {
						"currentGold": 496,
						"totalGold": 2846,
						"items": [
							123
						]
					},
					"3": {
						"currentGold": 455,
						"totalGold": 2055,
						"items": []
					},
					"4": {
						"currentGold": 323,
						"totalGold": 2873,
						"items": [
							138,
							3
						]
					},
					"5": {
						"currentGold": 13,
						"totalGold": 2998,
						"items": [
							0
						]
					},
					"6": {
						"currentGold": 518,
						"totalGold": 3948,
						"items": []
					},
					"7": {
						"currentGold": 1183,
						"totalGold": 4033,
						"items": [
							123,
							75
						]
					},
					"8": {
						"currentGold": 76,
						"totalGold": 3196,
						"items": [
							103
						]
					},
					"9": {
						"currentGold": 174,
						"totalGold": 5024,
						"items": [
							6,
							75
						]
					},
					"10": {
						"currentGold": 34,
						"totalGold": 2634,
						"items": [
							63
						]
					}
				}
			},
			{
				"participantFrames": {
					"1": {
						"currentGold": 313,
						"totalGold": 4518,
						"items": [
							60,
							1
						]
					},
					"2": {
						"currentGold": 824,
						"totalGold": 3174,
						"items": [
							123
						]
					},
					"3": {
						"currentGold": 105,
						"totalGold": 2290,
						"items": []
					},
					"4": {
						"currentGold": 560,
						"totalGold": 3110,
						"items": [
							138,
							3
						]
					},
					"5": {
						"currentGold": 323,
						"totalGold": 3308,
						"items": [
							0
						]
					},
					"6": {
						"currentGold": 822,
						"totalGold": 4252,
						"items": [
							35,
							39
						]
					},
					"7": {
						"currentGold": 1643,
						"totalGold": 4493,
						"items": [
							123,
							75
						]
					},
					"8": {
						"currentGold": 439,
						"totalGold": 3569,
						"items": [
							103,
							1
						]
					},
					"9": {
						"currentGold": 498,
						"totalGold": 5348,
						"items": [
							6,
							75,
							138
						]
					},
					"10": {
						"currentGold": 204,
						"totalGold": 2804,
						"items": [
							63,
							39
						]
					}
				}
			},
			{
				"participantFrames": {
					"1": {
						"currentGold": 878,
						"totalGold": 5093,
						"items": [
							60,
							1,
							81,
							21
						]
					},
					"2": {
						"currentGold": 1308,
						"totalGold": 3658,
						"items": [
							123
						]
					},
					"3": {
						"currentGold": 326,
						"totalGold": 2511,
						"items": [
							33
						]
					},
					"4": {
						"currentGold": 194,
						"totalGold": 3344,
						"items": [
							138,
							3
						]
					},
					"5": {
						"currentGold": 518,
						"totalGold": 3503,
						"items": [
							0
						]
					},
					"6": {
						"currentGold": 348,
						"totalGold": 4586,
						"items": [
							35,
							39
						]
					},
					"7": {
						"currentGold": 280,
						"totalGold": 4645,
						"items": [
							123,
							75
						]
					},
					"8": {
						"currentGold": 822,
						"totalGold": 3962,
						"items": [
							103,
							1
						]
					},
					"9": {
						"currentGold": 1489,
						"totalGold": 6339,
						"items": [
							6,
							75,
							138
						]
					},
					"10": {
						"currentGold": 525,
						"totalGold": 3125,
						"items": [
							63,
							39
						]
					}
				}
			},
			{
				"participantFrames": {
					"1": {
						"currentGold": 1570,
						"totalGold": 5785,
						"items": [
							60,
							1,
							81,
							21
						]
					},
					"2": {
						"currentGold": 1611,
						"totalGold": 3961,
						"items": [
							123
						]
					},
					"3": {
						"currentGold": 238,
						"totalGold": 2823,
						"items": [
							33
						]
					},
					"4": {
						"currentGold": 422,
						"totalGold": 3572,
						"items": [
							138,
							3
						]
					},
					"5": {
						"currentGold": 532,
						"totalGold": 4017,
						"items": [
							0
						]
					},
					"6": {
						"currentGold": 454,
						"totalGold": 5042,
						"items": [
							47
						]
					},
					"7": {
						"currentGold": 767,
						"totalGold": 5132,
						"items": [
							123,
							75,
							31
						]
					},
					"8": {
						"currentGold": 80,
						"totalGold": 4270,
						"items": [
							103,
							1
						]
					},
					"9": {
						"currentGold": 209,
						"totalGold": 7134,
						"items": [
							6,
							75,
							138
						]
					},
					"10": {
						"currentGold": 382,
						"totalGold": 3357,
						"items": [
							63,
							39
						]
					}
				}
			},
			{
				"participantFrames": {
					"1": {
						"currentGold": 582,
						"totalGold": 6107,
						"items": [
							60,
							1,
							81,
							21
						]
					},
					"2": {
						"currentGold": 228,
						"totalGold": 4178,
						"items": [
							123
						]
					},
					"3": {
						"currentGold": 333,
						"totalGold": 2993,
						"items": [
							33
						]
					},
					"4": {
						"currentGold": 168,
						"totalGold": 3943,
						"items": [
							138,
							3
						]
					},
					"5": {
						"currentGold": 698,
						"totalGold": 4183,
						"items": [
							0,
							33
						]
					},
					"6": {
						"currentGold": 1049,
						"totalGold": 5637,
						"items": [
							47
						]
					},
					"7": {
						"currentGold": 1149,
						"totalGold": 5514,
						"items": [
							123,
							75,
							31
						]
					},
					"8": {
						"currentGold": 341,
						"totalGold": 4606,
						"items": [
							133
						]
					},
					"9": {
						"currentGold": 1249,
						"totalGold": 8174,
						"items": [
							75,
							141,
							3
						]
					},
					"10": {
						"currentGold": 645,
						"totalGold": 3630,
						"items": [
							63,
							39
						]
					}
				}
			},
			{
				"participantFrames": {
					"1": {
						"currentGold": 1336,
						"totalGold": 7211,
						"items": [
							60,
							21,
							82
						]
					},
					"2": {
						"currentGold": 1227,
						"totalGold": 5177,
						"items": [
							129
						]
					},
					"3": {
						"currentGold": 148,
						"totalGold": 3283,
						"items": [
							33
						]
					},
					"4": {
						"currentGold": 290,
						"totalGold": 4065,
						"items": [
							139
						]
					},
					"5": {
						"currentGold": 138,
						"totalGold": 4473,
						"items": [
							0,
							33
						]
					},
					"6": {
						"currentGold": 75,
						"totalGold": 5913,
						"items": [
							47
						]
					},
					"7": {
						"currentGold": 1419,
						"totalGold": 5784,
						"items": [
							123,
							75,
							31
						]
					},
					"8": {
						"currentGold": 1061,
						"totalGold": 5326,
						"items": [
							133
						]
					},
					"9": {
						"currentGold": 1771,
						"totalGold": 9120,
						"items": [
							75,
							141,
							3
						]
					},
					"10": {
						"currentGold": 573,
						"totalGold": 4008,
						"items": [
							63,
							39
						]
					}
				}
			},
			{
				"participantFrames": {
					"1": {
						"currentGold": 680,
						"totalGold": 7355,
						"items": [
							60,
							21,
							82
						]
					},
					"2": {
						"currentGold": 141,
						"totalGold": 5316,
						"items": [
							129
						]
					},
					"3": {
						"currentGold": 428,
						"totalGold": 3563,
						"items": [
							33,
							39
						]
					},
					"4": {
						"currentGold": 706,
						"totalGold": 4481,
						"items": [
							139
						]
					},
					"5": {
						"currentGold": 487,
						"totalGold": 4822,
						"items": [
							0,
							33,
							1
						]
					},
					"6": {
						"currentGold": 377,
						"totalGold": 6290,
						"items": [
							47,
							63,
							72
						]
					},
					"7": {
						"currentGold": 438,
						"totalGold": 6228,
						"items": [
							123,
							75,
							31
						]
					},
					"8": {
						"currentGold": 1461,
						"totalGold": 5726,
						"items": [
							133
						]
					},
					"9": {
						"currentGold": 361,
						"totalGold": 9486,
						"items": [
							141,
							143
						]
					},
					"10": {
						"currentGold": 860,
						"totalGold": 4295,
						"items": [
							63,
							39
						]
					}
				}
			},
			{
				"participantFrames": {
					"1": {
						"currentGold": 1039,
						"totalGold": 7714,
						"items": [
							60,
							21,
							82,
							39
						]
					},
					"2": {
						"currentGold": 358,
						"totalGold": 5533,
						"items": [
							129,
							33
						]
					},
					"3": {
						"currentGold": 679,
						"totalGold": 3814,
						"items": [
							33,
							39
						]
					},
					"4": {
						"currentGold": 1051,
						"totalGold": 4826,
						"items": [
							139
						]
					},
					"5": {
						"currentGold": 11,
						"totalGold": 5161,
						"items": [
							0,
							33,
							1
						]
					},
					"6": {
						"currentGold": 590,
						"totalGold": 6503,
						"items": [
							47,
							63,
							72
						]
					},
					"7": {
						"currentGold": 760,
						"totalGold": 6550,
						"items": [
							75,
							129,
							87
						]
					},
					"8": {
						"currentGold": 75,
						"totalGold": 5940,
						"items": [
							133
						]
					},
					"9": {
						"currentGold": 788,
						"totalGold": 9913,
						"items": [
							141,
							143,
							18,
							7
						]
					},
					"10": {
						"currentGold": 50,
						"totalGold": 4435,
						"items": [
							63,
							39
						]
					}
				}
			},
			{
				"participantFrames": {
					"1": {
						"currentGold": 75,
						"totalGold": 8050,
						"items": [
							60,
							21,
							82,
							39
						]
					},
					"2": {
						"currentGold": 36,
						"totalGold": 5976,
						"items": [
							129,
							33
						]
					},
					"3": {
						"currentGold": 55,
						"totalGold": 4030,
						"items": [
							33,
							39
						]
					},
					"4": {
						"currentGold": 438,
						"totalGold": 5163,
						"items": [
							139
						]
					},
					"5": {
						"currentGold": 234,
						"totalGold": 5834,
						"items": [
							33,
							68
						]
					},
					"6": {
						"currentGold": 1927,
						"totalGold": 7840,
						"items": [
							47,
							63,
							72
						]
					},
					"7": {
						"currentGold": 93,
						"totalGold": 6983,
						"items": [
							75,
							129,
							87
						]
					},
					"8": {
						"currentGold": 1091,
						"totalGold": 6956,
						"items": [
							133,
							21,
							105
						]
					},
					"9": {
						"currentGold": 98,
						"totalGold": 10218,
						"items": [
							141,
							143,
							18,
							7
						]
					},
					"10": {
						"currentGold": 69,
						"totalGold": 4929,
						"items": [
							63,
							93
						]
					}
				}
			},
			{
				"participantFrames": {
					"1": {
						"currentGold": 587,
						"totalGold": 8562,
						"items": [
							21,
							82,
							110
						]
					},
					"2": {
						"currentGold": 374,
						"totalGold": 6314,
						"items": [
							129,
							33,
							31
						]
					},
					"3": {
						"currentGold": 367,
						"totalGold": 4342,
						"items": [
							33,
							39
						]
					},
					"4": {
						"currentGold": 860,
						"totalGold": 5585,
						"items": [
							139
						]
					},
					"5": {
						"currentGold": 511,
						"totalGold": 6186,
						"items": [
							33,
							68
						]
					},
					"6": {
						"currentGold": 301,
						"totalGold": 8089,
						"items": [
							47,
							63,
							72
						]
					},
					"7": {
						"currentGold": 316,
						"totalGold": 7206,
						"items": [
							75,
							129,
							87,
							74
						]
					},
					"8": {
						"currentGold": 433,
						"totalGold": 7273,
						"items": [
							133,
							21,
							105
						]
					},
					"9": {
						"currentGold": 741,
						"totalGold": 10861,
						"items": [
							141,
							143,
							18,
							7,
							35
						]
					},
					"10": {
						"currentGold": 209,
						"totalGold": 5069,
						"items": [
							63,
							93
						]
					}
				}
			},
			{
				"participantFrames": {
					"1": {
						"currentGold": 1008,
						"totalGold": 8983,
						"items": [
							21,
							82,
							110
						]
					},
					"2": {
						"currentGold": 146,
						"totalGold": 6561,
						"items": [
							129,
							33,
							31
						]
					},
					"3": {
						"currentGold": 507,
						"totalGold": 4482,
						"items": [
							33,
							39
						]
					},
					"4": {
						"currentGold": 1261,
						"totalGold": 5986,
						"items": [
							139
						]
					},
					"5": {
						"currentGold": 233,
						"totalGold": 6308,
						"items": [
							33,
							68
						]
					},
					"6": {
						"currentGold": 1055,
						"totalGold": 8843,
						"items": [
							47,
							63,
							126
						]
					},
					"7": {
						"currentGold": 885,
						"totalGold": 7775,
						"items": [
							75,
							129,
							87,
							74
						]
					},
					"8": {
						"currentGold": 1140,
						"totalGold": 7980,
						"items": [
							133,
							21,
							105,
							60
						]
					},
					"9": {
						"currentGold": 1417,
						"totalGold": 11537,
						"items": [
							141,
							143,
							18,
							7,
							35
						]
					},
					"10": {
						"currentGold": 462,
						"totalGold": 5322,
						"items": [
							63,
							93
						]
					}
				}
			},
			{
				"participantFrames": {
					"1": {
						"currentGold": 484,
						"totalGold": 9309,
						"items": [
							21,
							82,
							110
						]
					},
					"2": {
						"currentGold": 476,
						"totalGold": 6891,
						"items": [
							129,
							33,
							31
						]
					},
					"3": {
						"currentGold": 698,
						"totalGold": 4673,
						"items": [
							33,
							39
						]
					},
					"4": {
						"currentGold": 1684,
						"totalGold": 6409,
						"items": [
							139
						]
					},
					"5": {
						"currentGold": 489,
						"totalGold": 6564,
						"items": [
							33,
							68
						]
					},
					"6": {
						"currentGold": 205,
						"totalGold": 9168,
						"items": [
							47,
							63,
							126
						]
					},
					"7": {
						"currentGold": 408,
						"totalGold": 8148,
						"items": [
							75,
							129,
							87,
							74
						]
					},
					"8": {
						"currentGold": 521,
						"totalGold": 8161,
						"items": [
							133,
							21,
							105,
							60
						]
					},
					"9": {
						"currentGold": 506,
						"totalGold": 11800,
						"items": [
							141,
							143,
							18,
							7,
							35
						]
					},
					"10": {
						"currentGold": 182,
						"totalGold": 5517,
						"items": [
							63,
							93
						]
					}
				}
			},
			{
				"participantFrames": {
					"1": {
						"currentGold": 825,
						"totalGold": 9650,
						"items": [
							21,
							82,
							110,
							1
						]
					},
					"2": {
						"currentGold": 690,
						"totalGold": 7180,
						"items": [
							129,
							33,
							31
						]
					},
					"3": {
						"currentGold": 688,
						"totalGold": 4813,
						"items": [
							33,
							39
						]
					},
					"4": {
						"currentGold": 1995,
						"totalGold": 6720,
						"items": [
							139
						]
					},
					"5": {
						"currentGold": 307,
						"totalGold": 6882,
						"items": [
							33,
							68
						]
					},
					"6": {
						"currentGold": 1018,
						"totalGold": 9981,
						"items": [
							47,
							63,
							126,
							31
						]
					},
					"7": {
						"currentGold": 968,
						"totalGold": 8708,
						"items": [
							129,
							87,
							79
						]
					},
					"8": {
						"currentGold": 1434,
						"totalGold": 9074,
						"items": [
							133,
							21,
							105,
							60,
							39
						]
					},
					"9": {
						"currentGold": 1008,
						"totalGold": 12302,
						"items": [
							141,
							143,
							18,
							53
						]
					},
					"10": {
						"currentGold": 763,
						"totalGold": 6098,
						"items": [
							63,
							93,
							39
						]
					}
				}
			},
			{
				"participantFrames": {
					"1": {
						"currentGold": 894,
						"totalGold": 9719,
						"items": [
							21,
							82,
							110,
							1
						]
					},
					"2": {
						"currentGold": 759,
						"totalGold": 7249,
						"items": [
							129,
							33,
							31
						]
					},
					"3": {
						"currentGold": 768,
						"totalGold": 4893,
						"items": [
							33,
							39
						]
					},
					"4": {
						"currentGold": 214,
						"totalGold": 6789,
						"items": [
							139
						]
					},
					"5": {
						"currentGold": 376,
						"totalGold": 6951,
						"items": [
							33,
							68,
							0
						]
					},
					"6": {
						"currentGold": 634,
						"totalGold": 10471,
						"items": [
							47,
							63,
							126,
							31
						]
					},
					"7": {
						"currentGold": 1478,
						"totalGold": 9217,
						"items": [
							129,
							87,
							79
						]
					},
					"8": {
						"currentGold": 1817,
						"totalGold": 9456,
						"items": [
							133,
							21,
							105,
							60,
							39
						]
					},
					"9": {
						"currentGold": 1352,
						"totalGold": 12646,
						"items": [
							141,
							143,
							18,
							53
						]
					},
					"10": {
						"currentGold": 950,
						"totalGold": 6284,
						"items": [
							63,
							93,
							39
						]
					}
				}
			}
		]
	}
}